{
  "main": {
    "id": "f3d8a47ced3d79ab",
    "type": "split",
    "children": [
      {
        "id": "b0e57289284301ed",
        "type": "tabs",
        "children": [
          {
            "id": "075cd70aaaac99e8",
            "type": "leaf",
            "state": {
              "type": "empty",
              "state": {}
            }
          }
        ]
      }
    ],
    "direction": "vertical"
  },
  "left": {
    "id": "088d9c34d8fae636",
    "type": "split",
    "children": [
      {
        "id": "f6a797444bd8bee1",
        "type": "tabs",
        "children": [
          {
            "id": "84745a00b041d5bb",
            "type": "leaf",
            "state": {
              "type": "search",
              "state": {
                "query": "tag:#plugins",
                "matchingCase": false,
                "explainSearch": false,
                "collapseAll": false,
                "extraContext": false,
                "sortOrder": "alphabetical"
              }
            }
          },
          {
            "id": "9b2dfc471fa33822",
            "type": "leaf",
            "state": {
              "type": "file-explorer",
              "state": {
                "sortOrder": "alphabetical"
              }
            }
          },
          {
            "id": "6fbe40aec2afce1a",
            "type": "leaf",
            "state": {
              "type": "bookmarks",
              "state": {}
            }
          }
        ],
        "currentTab": 1
      }
    ],
    "direction": "horizontal",
    "width": 403,
    "collapsed": true
  },
  "right": {
    "id": "df19b8e4e908e17a",
    "type": "split",
    "children": [
      {
        "id": "32d0cc80d95afd85",
        "type": "tabs",
        "dimension": 34.98062015503876,
        "children": [
          {
            "id": "aa1cfa46beb0d678",
            "type": "leaf",
            "state": {
              "type": "calendar",
              "state": {}
            }
          },
          {
            "id": "2af48e3b60eae90c",
            "type": "leaf",
            "state": {
              "type": "outline",
              "state": {
                "file": "pages/library.md"
              }
            }
          },
          {
            "id": "a6c6ddf9e373df0b",
            "type": "leaf",
            "state": {
              "type": "backlink",
              "state": {
                "file": "pages/library.md",
                "collapseAll": false,
                "extraContext": false,
                "sortOrder": "alphabetical",
                "showSearch": false,
                "searchQuery": "",
                "backlinkCollapsed": false,
                "unlinkedCollapsed": true
              }
            }
          },
          {
            "id": "3a6d2f426e0cbbc0",
            "type": "leaf",
            "state": {
              "type": "outgoing-link",
              "state": {
                "file": "pages/library.md",
                "linksCollapsed": false,
                "unlinkedCollapsed": true
              }
            }
          }
        ]
      },
      {
        "id": "b82c3f6e69990012",
        "type": "tabs",
        "dimension": 65.01937984496124,
        "children": [
          {
            "id": "610d7e0d24257c16",
            "type": "leaf",
            "state": {
              "type": "graph",
              "state": {}
            }
          },
          {
            "id": "02c928e7bd84b856",
            "type": "leaf",
            "state": {
              "type": "localgraph",
              "state": {
                "file": "pages/library.md",
                "options": {
                  "collapse-filter": true,
                  "search": "",
                  "localJumps": 1,
                  "localBacklinks": true,
                  "localForelinks": true,
                  "localInterlinks": false,
                  "showTags": false,
                  "showAttachments": false,
                  "hideUnresolved": false,
                  "collapse-color-groups": true,
                  "colorGroups": [],
                  "collapse-display": true,
                  "showArrow": false,
                  "textFadeMultiplier": 0,
                  "nodeSizeMultiplier": 1,
                  "lineSizeMultiplier": 1,
                  "collapse-forces": true,
                  "centerStrength": 0.518713248970312,
                  "repelStrength": 10,
                  "linkStrength": 1,
                  "linkDistance": 250,
                  "scale": 0.5087618855792589,
                  "close": true
                }
              }
            }
          },
          {
            "id": "c6bbf630615cde16",
            "type": "leaf",
            "state": {
              "type": "tag",
              "state": {
                "sortOrder": "frequency",
                "useHierarchy": true
              }
            }
          }
        ],
        "currentTab": 1
      }
    ],
    "direction": "horizontal",
    "width": 352,
    "collapsed": true
  },
  "left-ribbon": {
    "hiddenItems": {
      "homepage:Open homepage": false,
      "obsidian-kanban:Create new board": true,
      "daily-notes:Open today's daily note": false,
      "switcher:Open quick switcher": false,
      "graph:Open graph view": false,
      "templates:Insert template": true,
      "command-palette:Open command palette": true,
      "obsidian-excalidraw-plugin:Create new drawing": true,
      "obsidian-file-cleaner:Clean files": true,
      "templater-obsidian:Templater": false,
      "obsidian-book-search-plugin:Create new book note": false
    }
  },
  "active": "9b2dfc471fa33822",
  "lastOpenFiles": [
    "library/Curso de Física Básica.md",
    "library/The Feynman Lectures on Physics.md",
    "library/The Art of Computer Programming - Vol. 01.md",
    "library/Teoria Unificada dos Conjuntos.md",
    "library/Só pode ser brincadeira, Sr. Feynman!.md",
    "library/Principles of Mathematical Analysis.md",
    "library/Princípios Matemáticos de Filosofia Natural - Livro II e III.md",
    "library/Princípios Matemáticos de Filosofia Natural - Livro I.md",
    "library/Os melhores textos de Richard P. Feynman.md",
    "library/Os Elementos.md",
    "library/Mecânica Newtoniana, Lagrangiana e Hamiltoniana.md",
    "library/Lógica Matemática.md",
    "library/Fundamentos de Matemática Elementar - Vol. 01.md",
    "library/Fundamentos de Matemática Elementar.md",
    "library/Curso de Física Básica - Vol. 04.md",
    "library/Curso de Física Básica - Vol. 03.md",
    "library/Curso de Física Básica - Vol. 02.md",
    "library/Curso de Física Básica - Vol. 01.md",
    "library/The Feynman Lectures on Physics - Vol. 03.md",
    "library/The Feynman Lectures on Physics - Vol. 02.md",
    "library/The Feynman Lectures on Physics - Vol. 01.md",
    "templates/literature_template.md",
    "pages/library.md",
    "templates/daily_template.md",
    "pages/home.md",
    "pages/mathematics.md",
    "attachments/excalidraw",
    "attachments/banners/homepage.gif",
    "attachments/banners/homepage.gif.crdownload",
    "attachments/banners/library.avif",
    "attachments/homepage/banner.gif",
    "attachments/homepage/banner.gif.crdownload",
    "attachments/banners",
    "attachments/bookshelf.jpg",
    "attachments/banners/library.avif.crdownload",
    "attachments/bookshelf.jpg.crdownload",
    "attachments/banners/homepage.png",
    "attachments/banners/homepage.png.crdownload",
    "attachments/banners",
    "attachments/New folder",
    "library"
  ]
}